Flask_ottawa_transit-1.0.dist-info/METADATA
Flask_ottawa_transit-1.0.dist-info/RECORD
Flask_ottawa_transit-1.0.dist-info/WHEEL
Flask_ottawa_transit-1.0.dist-info/top_level.txt
flask_ottawa_transit/__init__.py
