Metadata-Version: 2.1
Name: Flask-ottawa-transit
Version: 1.0
Summary: Flask extension around the python-ottawa-transit module
Home-page: http://github.com/buckley-w-david/Flask-ottawa-transit
Author: David Buckley
Author-email: buckley.w.david@gmail.com
License: MIT
Platform: any
Classifier: Environment :: Web Environment
Classifier: Intended Audience :: Developers
Classifier: License :: OSI Approved :: BSD License
Classifier: Operating System :: OS Independent
Classifier: Programming Language :: Python
Classifier: Topic :: Internet :: WWW/HTTP :: Dynamic Content
Classifier: Topic :: Software Development :: Libraries :: Python Modules
Requires-Dist: Flask (>=1.0)
Requires-Dist: python-ottawa-transit (>=0.2.0)
